{
  "id": "deck_deep_friends_01",
  "title": "Level 2: Connection",
  "description": "For FRIENDS. Dig deeper. Ask the questions you usually avoid and strengthen your bond.",
  "game_engine_id": "deep_dive",
  "game_engine_type": "simple_flip",
  "is_system": true,
  "created_at": "2023-01-10T11:00:00Z",
  "cards": [
    {
      "content": "What is the last lie you told?",
      "back": "Who did you tell it to?",
      "meta": {}
    },
    {
      "content": "What is a feeling you miss?",
      "back": "Describe it.",
      "meta": {}
    },
    {
      "content": "What is the hardest truth you've had to accept about yourself?",
      "back": "Take your time.",
      "meta": {}
    },
    {
      "content": "Who in your life do you feel most yourself around?",
      "back": "Why them?",
      "meta": {}
    },
    {
      "content": "WILDCARD",
      "back": "Write a note to the other person. Don't let them read it until they leave.",
      "meta": {}
    },
    {
      "content": "What is a pain you are currently healing from?",
      "back": "You don't have to share details if you don't want to.",
      "meta": {}
    },
    {
      "content": "What is your biggest fear regarding our friendship?",
      "back": "Both players answer.",
      "meta": {}
    },
    {
      "content": "When was the last time you felt truly proud of yourself?",
      "back": "Brag a little.",
      "meta": {}
    },
    {
      "content": "What is a dream you've let go of?",
      "back": "Why did you let it go?",
      "meta": {}
    },
    {
      "content": "If you could apologize to one person, who would it be?",
      "back": "What would you say?",
      "meta": {}
    },
    {
      "content": "What part of your life do you feel is currently missing?",
      "back": "Love? Purpose? Fun?",
      "meta": {}
    },
    {
      "content": "WILDCARD",
      "back": "Give the other person a genuine compliment you've never said before.",
      "meta": {}
    },
    {
      "content": "Are you holding onto a grudge?",
      "back": "Does it serve you?",
      "meta": {}
    },
    {
      "content": "What is the biggest mistake you've made in the last year?",
      "back": "What did you learn?",
      "meta": {}
    },
    {
      "content": "Do you think you are easy or hard to love?",
      "back": "Explain why.",
      "meta": {}
    },
    {
      "content": "What is something you wish you could tell your parents?",
      "back": "Why haven't you?",
      "meta": {}
    },
    {
      "content": "When was the last time you cried?",
      "back": "What caused it?",
      "meta": {}
    },
    {
      "content": "What is one thing you need to forgive yourself for?",
      "back": "Both players answer.",
      "meta": {}
    },
    {
      "content": "What is the most misunderstood thing about you?",
      "back": "Clear the air.",
      "meta": {}
    },
    {
      "content": "Who is someone you miss, but don't talk to anymore?",
      "back": "Why did you drift apart?",
      "meta": {}
    },
    {
      "content": "WILDCARD",
      "back": "Scroll to the first photo of us together on your phone. Show it.",
      "meta": {}
    },
    {
      "content": "What is a compliment you struggle to accept?",
      "back": "Why do you reject it?",
      "meta": {}
    },
    {
      "content": "If you died tomorrow, what would be your biggest regret?",
      "back": "Both players answer.",
      "meta": {}
    },
    {
      "content": "What is something you are currently procrastinating?",
      "back": "Is it out of fear?",
      "meta": {}
    },
    {
      "content": "Do you feel like you are where you're supposed to be in life?",
      "back": "Yes or No.",
      "meta": {}
    },
    {
      "content": "What is a habit you are trying to break?",
      "back": "How is it going?",
      "meta": {}
    },
    {
      "content": "What makes you feel lonely?",
      "back": "Even when around people.",
      "meta": {}
    },
    {
      "content": "What is the nicest thing anyone has ever done for you?",
      "back": "Both players answer.",
      "meta": {}
    },
    {
      "content": "How have you changed in the last year?",
      "back": "For better or worse?",
      "meta": {}
    },
    {
      "content": "WILDCARD",
      "back": "Admit one thing you admire about the other person.",
      "meta": {}
    },
    {
      "content": "What is a question you are afraid to ask me?",
      "back": "Ask it now.",
      "meta": {}
    },
    {
      "content": "Are you happy with who you are becoming?",
      "back": "Be honest.",
      "meta": {}
    },
    {
      "content": "What keeps you up at night?",
      "back": "Worries or dreams?",
      "meta": {}
    },
    {
      "content": "If you could change one thing about your childhood, what would it be?",
      "back": "Both players answer.",
      "meta": {}
    },
    {
      "content": "What is something you take for granted?",
      "back": "Acknowledge it.",
      "meta": {}
    },
    {
      "content": "What is the best advice you've ever received?",
      "back": "Did you follow it?",
      "meta": {}
    },
    {
      "content": "What is something you lied about to protect someone's feelings?",
      "back": "Was it worth it?",
      "meta": {}
    },
    {
      "content": "When do you feel most beautiful?",
      "back": "Internal or external.",
      "meta": {}
    },
    {
      "content": "What is a boundary you need to set?",
      "back": "With friends, family, or work.",
      "meta": {}
    },
    {
      "content": "WILDCARD",
      "back": "Hug for 20 seconds. If not comfortable, high five.",
      "meta": {}
    },
    {
      "content": "What is something you pretend to understand but don't?",
      "back": "Confess.",
      "meta": {}
    },
    {
      "content": "What is your definition of success?",
      "back": "Has it changed?",
      "meta": {}
    },
    {
      "content": "What is something you want to be remembered for?",
      "back": "Your legacy.",
      "meta": {}
    },
    {
      "content": "Who was your first heartbreak?",
      "back": "Describe the feeling.",
      "meta": {}
    },
    {
      "content": "What is something you are envious of?",
      "back": "Jealousy is a map.",
      "meta": {}
    },
    {
      "content": "If you could have a conversation with anyone living or dead, who?",
      "back": "What would you ask?",
      "meta": {}
    },
    {
      "content": "What is one thing you would change about our friendship?",
      "back": "Constructive criticism.",
      "meta": {}
    },
    {
      "content": "Do you think we will be friends in 10 years?",
      "back": "Why or why not?",
      "meta": {}
    },
    {
      "content": "What is the most brave thing you have ever done?",
      "back": "Share the story.",
      "meta": {}
    },
    {
      "content": "What is a smell that triggers a memory for you?",
      "back": "Describe the memory.",
      "meta": {}
    },
    {
      "content": "Who was your favorite teacher and why?",
      "back": "What did they teach you?",
      "meta": {}
    },
    {
      "content": "What is the most physical pain you've ever felt?",
      "back": "Describe it.",
      "meta": {}
    },
    {
      "content": "Have you ever seen a ghost?",
      "back": "Or had a paranormal experience?",
      "meta": {}
    },
    {
      "content": "What is a song that makes you cry?",
      "back": "Why that song?",
      "meta": {}
    },
    {
      "content": "What is your definition of a 'good life'?",
      "back": "Simplicity? Wealth? Adventure?",
      "meta": {}
    },
    {
      "content": "When do you feel most lonely?",
      "back": "In a crowd or alone?",
      "meta": {}
    },
    {
      "content": "What is something you are proud of but never talk about?",
      "back": "Brag now.",
      "meta": {}
    },
    {
      "content": "What is the biggest risk you've ever taken?",
      "back": "Did it pay off?",
      "meta": {}
    },
    {
      "content": "If you could change your name, what would it be?",
      "back": "Why that name?",
      "meta": {}
    },
    {
      "content": "What is something you need to let go of?",
      "back": "Release it.",
      "meta": {}
    }
  ]
}
